factbase/__init__.py
cleip-0.0.1.dist-info/METADATA
cleip-0.0.1.dist-info/WHEEL
cleip-0.0.1.dist-info/top_level.txt
cleip-0.0.1.dist-info/RECORD
